bedrock/__init__.py
bedrock/plot.py
bedrock/gi/__init__.py
bedrock/gi/bedrock-gi-schema.json
bedrock/gi/concatenate.py
bedrock/gi/gis_geometry.py
bedrock/gi/main.py
bedrock/gi/schemas.py
bedrock/gi/sqlmodels.py
bedrock/gi/validate.py
bedrock/gi/write.py
bedrock/gi/ags/__init__.py
bedrock/gi/ags/ags3_data_dictionary.json
bedrock/gi/ags/ags4_data_dictionary.json
bedrock/gi/ags/read.py
bedrock/gi/ags/schemas.py
bedrock/gi/ags/transform.py
bedrock/gi/ags/validate.py
bedrock_gi-0.1.4.dist-info/METADATA
bedrock_gi-0.1.4.dist-info/WHEEL
bedrock_gi-0.1.4.dist-info/entry_points.txt
bedrock_gi-0.1.4.dist-info/licenses/LICENSE
bedrock_gi-0.1.4.dist-info/RECORD
