Metadata-Version: 2.4
Name: bedrock-gi
Version: 0.1.4
Summary: Bedrock, the Open Source Foundation for Ground Investigation Data
Project-URL: Homepage, https://bedrock.engineer/
Project-URL: Source, https://github.com/bedrock-gi/bedrock-gi
Project-URL: Documentation, https://bedrock.engineer/docs/
Project-URL: Tracker, https://github.com/bedrock-gi/bedrock-gi/issues
Author-email: Bedrock <info@bedrock.engineer>
License: Apache Software License (Apache 2.0)
License-File: LICENSE
Keywords: aec,ags,bedrock,bim,engineering geology,geo-bim,geotech,geotechnical data,geotechnical engineering,gi data,gis,ground engineering,ground investigation,ground investigation data
Classifier: Development Status :: 2 - Pre-Alpha
Classifier: License :: OSI Approved :: Apache Software License
Classifier: Operating System :: OS Independent
Classifier: Programming Language :: Python :: 3
Requires-Python: >=3.9
Requires-Dist: duckdb~=1.0
Requires-Dist: geopandas~=1.0
Requires-Dist: openpyxl~=3.0
Requires-Dist: pandera>=0.23.0
Requires-Dist: python-ags4~=1.0
Requires-Dist: sqlglot>=26.12.0
Requires-Dist: sqlmodel>=0.0.22
